scif/__init__.py
scif/defaults.py
scif/version.py
scif/client/__init__.py
scif/client/dump.py
scif/client/execute.py
scif/client/help.py
scif/client/inspect.py
scif/client/install.py
scif/client/list.py
scif/client/preview.py
scif/client/pyshell.py
scif/client/run.py
scif/client/shell.py
scif/client/test.py
scif/client/utils.py
scif/logger/__init__.py
scif/logger/message.py
scif/logger/progress.py
scif/logger/spinner.py
scif/main/__init__.py
scif/main/apps.py
scif/main/base.py
scif/main/commands.py
scif/main/environment.py
scif/main/helpers.py
scif/main/install.py
scif/main/parser.py
scif/main/preview.py
scif/main/setup.py
scif/tests/__init__.py
scif/tests/functions.sh
scif/tests/test_exec.sh
scif/tests/test_help.sh
scif/tests/test_run.sh
scif/tests/test_tests.sh
scif/tests/test_utils.py
scif/utils/__init__.py
scif/utils/fileio.py
scif/utils/terminal.py
scif-0.0.84.dist-info/LICENSE
scif-0.0.84.dist-info/METADATA
scif-0.0.84.dist-info/WHEEL
scif-0.0.84.dist-info/entry_points.txt
scif-0.0.84.dist-info/top_level.txt
scif-0.0.84.dist-info/RECORD
