Metadata-Version: 2.1
Name: scif
Version: 0.0.84
Summary: a filesystem organization for scientific software and metadata
Home-page: http://www.github.com/vsoch/scif
Author: Vanessa Sochat
Author-email: vsochat@stanford.edu
Maintainer: Vanessa Sochat
Maintainer-email: vsochat@stanford.edu
License: LICENSE
Keywords: the scientific filesystem
Classifier: Intended Audience :: Science/Research
Classifier: Intended Audience :: Developers
Classifier: License :: OSI Approved :: Mozilla Public License 2.0 (MPL 2.0)
Classifier: Programming Language :: C
Classifier: Programming Language :: Python
Classifier: Topic :: Software Development
Classifier: Topic :: Scientific/Engineering
Classifier: Operating System :: Unix
Classifier: Programming Language :: Python :: 3
License-File: LICENSE
Requires-Dist: six >=1.7.0
Requires-Dist: pygments >=2.1.3
Provides-Extra: all
Requires-Dist: six >=1.7.0 ; extra == 'all'
Requires-Dist: pygments >=2.1.3 ; extra == 'all'
